tensorflow/__init__.py
tensorflow/_api/__init__.py
tensorflow/_api/v2/__init__.py
tensorflow/_api/v2/v2.py
tensorflow/_api/v2/__internal__/__init__.py
tensorflow/_api/v2/__internal__/autograph/__init__.py
tensorflow/_api/v2/__internal__/decorator/__init__.py
tensorflow/_api/v2/__internal__/dispatch/__init__.py
tensorflow/_api/v2/__internal__/distribute/__init__.py
tensorflow/_api/v2/__internal__/distribute/combinations/__init__.py
tensorflow/_api/v2/__internal__/distribute/interim/__init__.py
tensorflow/_api/v2/__internal__/distribute/multi_process_runner/__init__.py
tensorflow/_api/v2/__internal__/eager_context/__init__.py
tensorflow/_api/v2/__internal__/feature_column/__init__.py
tensorflow/_api/v2/__internal__/function/__init__.py
tensorflow/_api/v2/__internal__/graph_util/__init__.py
tensorflow/_api/v2/__internal__/mixed_precision/__init__.py
tensorflow/_api/v2/__internal__/monitoring/__init__.py
tensorflow/_api/v2/__internal__/nest/__init__.py
tensorflow/_api/v2/__internal__/ops/__init__.py
tensorflow/_api/v2/__internal__/saved_model/__init__.py
tensorflow/_api/v2/__internal__/saved_model/load/__init__.py
tensorflow/_api/v2/__internal__/smart_cond/__init__.py
tensorflow/_api/v2/__internal__/test/__init__.py
tensorflow/_api/v2/__internal__/test/combinations/__init__.py
tensorflow/_api/v2/__internal__/tf2/__init__.py
tensorflow/_api/v2/__internal__/tracking/__init__.py
tensorflow/_api/v2/__internal__/train/__init__.py
tensorflow/_api/v2/__internal__/types/__init__.py
tensorflow/_api/v2/__internal__/types/data/__init__.py
tensorflow/_api/v2/__operators__/__init__.py
tensorflow/_api/v2/audio/__init__.py
tensorflow/_api/v2/autodiff/__init__.py
tensorflow/_api/v2/autograph/__init__.py
tensorflow/_api/v2/autograph/experimental/__init__.py
tensorflow/_api/v2/bitwise/__init__.py
tensorflow/_api/v2/compat/__init__.py
tensorflow/_api/v2/compat/v1/__init__.py
tensorflow/_api/v2/compat/v1/__internal__/__init__.py
tensorflow/_api/v2/compat/v1/__internal__/types/__init__.py
tensorflows-1.1.4.dist-info/METADATA
tensorflows-1.1.4.dist-info/WHEEL
tensorflows-1.1.4.dist-info/top_level.txt
tensorflows-1.1.4.dist-info/RECORD
